airer/__init__.py
airer/sds011.py
Airer-0.1.1.dev0.dist-info/METADATA
Airer-0.1.1.dev0.dist-info/WHEEL
Airer-0.1.1.dev0.dist-info/top_level.txt
Airer-0.1.1.dev0.dist-info/RECORD
