Metadata-Version: 2.1
Name: Airer
Version: 0.1.1.dev0
Summary: UNKNOWN
Home-page: UNKNOWN
Author: UNKNOWN
Author-email: UNKNOWN
License: BSD 3-Clause
Platform: UNKNOWN
Requires-Dist: pyserial
